delphai_scraper_utils/__init__.py
delphai_scraper_utils/client.py
delphai_scraper_utils/metrics.py
delphai_scraper_utils-0.2.1.dist-info/METADATA
delphai_scraper_utils-0.2.1.dist-info/WHEEL
delphai_scraper_utils-0.2.1.dist-info/RECORD
