Metadata-Version: 2.1
Name: delphai-scraper-utils
Version: 0.2.1
Summary: 
Author: Frederik Schwabe
Author-email: frederik@delphai.com
Requires-Python: >=3.11,<4.0
Classifier: Programming Language :: Python :: 3
Classifier: Programming Language :: Python :: 3.11
Classifier: Programming Language :: Python :: 3.12
Requires-Dist: async-lru (>=2.0.5,<3.0.0)
Requires-Dist: httpx (>=0.24,<=0.27.2)
Requires-Dist: prometheus-client (>=0,<1)
Requires-Dist: protego (>=0.4.0,<0.5.0)
Requires-Dist: tenacity (>=8,<9)
